ion_detective/__init__.py
ion_detective/ion_detective.py
ion_detective/ion_detector.py
ion_detective/utils.py
ion_detective-0.2.0.dist-info/LICENSE
ion_detective-0.2.0.dist-info/METADATA
ion_detective-0.2.0.dist-info/WHEEL
ion_detective-0.2.0.dist-info/top_level.txt
ion_detective-0.2.0.dist-info/RECORD
