Metadata-Version: 2.1
Name: ion-detective
Version: 0.2.0
Summary: Virtual laboratory for chemistry students to simulate qualitative ion analysis.
Home-page: https://github.com/Dom1L/ion_detective
Author: Dominik Lemm
Author-email: lemm92.d@gmail.com
License: gpl-3.0
Platform: UNKNOWN
Classifier: Programming Language :: Python :: 3
Classifier: Operating System :: OS Independent
